{
    "testphp.vulnweb.com": [
        {
            "subdomain": "http://testphp.vulnweb.com",
            "status_code": "200"
        }
    ]
}{
    "testphp.vulnweb.com": [
        {
            "subdomain": "http://testphp.vulnweb.com",
            "status_code": "200"
        }
    ]
}{
    "newegg.com": []
}{
    "newegg.com": [
        {
            "subdomain": "https://chat.newegg.com",
            "status_code": "403"
        },
        {
            "subdomain": "https://e11ssltestp.newegg.com",
            "status_code": "403"
        },
        {
            "subdomain": "https://e11sellerportaltest.newegg.com",
            "status_code": "403"
        },
        {
            "subdomain": "https://developer.newegg.com",
            "status_code": "403"
        },
        {
            "subdomain": "https://e11stgtest-m.newegg.com",
            "status_code": "403"
        },
        {
            "subdomain": "https://e11sellerimagestest.newegg.com",
            "status_code": "200"
        },
        {
            "subdomain": "https://e11stgtest-image.newegg.com",
            "status_code": "403"
        },
        {
            "subdomain": "https://as2.newegg.com",
            "status_code": "403"
        },
        {
            "subdomain": "https://api.newegg.com",
            "status_code": "200"
        },
        {
            "subdomain": "https://carriercentral.newegg.com",
            "status_code": "403"
        },
        {
            "subdomain": "https://chattest.newegg.com",
            "status_code": "403"
        },
        {
            "subdomain": "https://e11stgtest-secure.newegg.com",
            "status_code": "403"
        },
        {
            "subdomain": "https://e11stgtest.newegg.com",
            "status_code": "403"
        },
        {
            "subdomain": "https://e11ssltestm.newegg.com",
            "status_code": "403"
        },
        {
            "subdomain": "https://download.newegg.com",
            "status_code": "403"
        },
        {
            "subdomain": "https://e11wwwtest.newegg.com",
            "status_code": "403"
        },
        {
            "subdomain": "https://e11ssltest.newegg.com",
            "status_code": "403"
        },
        {
            "subdomain": "https://e11stgtest-secure-m.newegg.com",
            "status_code": "403"
        },
        {
            "subdomain": "https://corporate.newegg.com",
            "status_code": "302"
        },
        {
            "subdomain": "https://bridge.newegg.com",
            "status_code": "302"
        },
        {
            "subdomain": "https://cloudfront.newegg.com",
            "status_code": "403"
        },
        {
            "subdomain": "https://e11wwwtestp.newegg.com",
            "status_code": "403"
        },
        {
            "subdomain": "https://ec-apis.newegg.com",
            "status_code": "403"
        },
        {
            "subdomain": "https://apis.newegg.com",
            "status_code": "200"
        },
        {
            "subdomain": "https://eniac.newegg.com",
            "status_code": "301"
        },
        {
            "subdomain": "https://helptest.newegg.com",
            "status_code": "301"
        },
        {
            "subdomain": "https://ih.newegg.com",
            "status_code": "403"
        },
        {
            "subdomain": "https://images10.newegg.com",
            "status_code": "403"
        },
        {
            "subdomain": "https://gamecrate.newegg.com",
            "status_code": "302"
        },
        {
            "subdomain": "https://hostmaster@newegg.com",
            "status_code": "301"
        },
        {
            "subdomain": "https://investors.newegg.com",
            "status_code": "403"
        },
        {
            "subdomain": "https://i.promo-flash.newegg.com",
            "status_code": "403"
        },
        {
            "subdomain": "https://i.promo.global.newegg.com",
            "status_code": "403"
        },
        {
            "subdomain": "https://help.newegg.com",
            "status_code": "301"
        },
        {
            "subdomain": "https://edi04.newegg.com",
            "status_code": "200"
        },
        {
            "subdomain": "https://live.stream.newegg.com",
            "status_code": "403"
        },
        {
            "subdomain": "https://i.promo.newegg.com",
            "status_code": "403"
        },
        {
            "subdomain": "https://media.newegg.com",
            "status_code": "403"
        },
        {
            "subdomain": "https://newegg.com",
            "status_code": "403"
        },
        {
            "subdomain": "https://metrics.newegg.com",
            "status_code": "400"
        },
        {
            "subdomain": "https://metrics-staging.newegg.com",
            "status_code": "400"
        },
        {
            "subdomain": "https://m.newegg.com",
            "status_code": "403"
        },
        {
            "subdomain": "https://kb.newegg.com",
            "status_code": "301"
        },
        {
            "subdomain": "https://ows1.newegg.com",
            "status_code": "403"
        },
        {
            "subdomain": "https://logistics.newegg.com",
            "status_code": "301"
        },
        {
            "subdomain": "https://l.promo-flash.newegg.com",
            "status_code": "302"
        },
        {
            "subdomain": "https://mkplapp.newegg.com",
            "status_code": "200"
        },
        {
            "subdomain": "https://l.promo.newegg.com",
            "status_code": "302"
        },
        {
            "subdomain": "https://jobs.newegg.com",
            "status_code": "200"
        },
        {
            "subdomain": "https://l.promo.global.newegg.com",
            "status_code": "302"
        },
        {
            "subdomain": "https://pmtcardstestp.newegg.com",
            "status_code": "403"
        },
        {
            "subdomain": "https://pmtcards.newegg.com",
            "status_code": "403"
        },
        {
            "subdomain": "https://promotions.newegg.com",
            "status_code": "403"
        },
        {
            "subdomain": "https://pf.newegg.com",
            "status_code": "403"
        },
        {
            "subdomain": "https://pmtcardstest.newegg.com",
            "status_code": "403"
        },
        {
            "subdomain": "https://secure.m.newegg.com",
            "status_code": "403"
        },
        {
            "subdomain": "https://sellerimages.newegg.com",
            "status_code": "200"
        },
        {
            "subdomain": "https://secure.newegg.com",
            "status_code": "403"
        },
        {
            "subdomain": "https://selphie.y.zhao@newegg.com",
            "status_code": "403"
        },
        {
            "subdomain": "https://partner.newegg.com",
            "status_code": "200"
        },
        {
            "subdomain": "https://push.stream.newegg.com",
            "status_code": "403"
        },
        {
            "subdomain": "https://ssl-images.newegg.com",
            "status_code": "403"
        },
        {
            "subdomain": "https://stagingapis.newegg.com",
            "status_code": "403"
        },
        {
            "subdomain": "https://push.newegg.com",
            "status_code": "200"
        },
        {
            "subdomain": "https://sandboxapis.newegg.com",
            "status_code": "200"
        },
        {
            "subdomain": "https://s.promo-flash.newegg.com",
            "status_code": "302"
        },
        {
            "subdomain": "https://s.promo.global.newegg.com",
            "status_code": "302"
        },
        {
            "subdomain": "https://video.stream.newegg.com",
            "status_code": "403"
        },
        {
            "subdomain": "https://s.promo.newegg.com",
            "status_code": "302"
        },
        {
            "subdomain": "https://www.newegg.com",
            "status_code": "403"
        },
        {
            "subdomain": "https://sellerportal.newegg.com",
            "status_code": "301"
        },
        {
            "subdomain": "https://www2.newegg.com",
            "status_code": "403"
        },
        {
            "subdomain": "https://vendorportal.newegg.com",
            "status_code": "200"
        },
        {
            "subdomain": "https://w.promo.newegg.com",
            "status_code": "302"
        },
        {
            "subdomain": "https://staffing.newegg.com",
            "status_code": "200"
        },
        {
            "subdomain": "https://w.promo-flash.newegg.com",
            "status_code": "302"
        },
        {
            "subdomain": "https://w.promo.global.newegg.com",
            "status_code": "302"
        },
        {
            "subdomain": "https://x.promo.newegg.com",
            "status_code": "302"
        },
        {
            "subdomain": "https://x.promo-flash.newegg.com",
            "status_code": "302"
        },
        {
            "subdomain": "https://x.promo.global.newegg.com",
            "status_code": "302"
        }
    ]
}